.gitignore
CHANGES.txt
README.txt
buildout.cfg
setup.py
hostout/__init__.py
hostout.ubuntu.egg-info/PKG-INFO
hostout.ubuntu.egg-info/SOURCES.txt
hostout.ubuntu.egg-info/dependency_links.txt
hostout.ubuntu.egg-info/entry_points.txt
hostout.ubuntu.egg-info/namespace_packages.txt
hostout.ubuntu.egg-info/not-zip-safe
hostout.ubuntu.egg-info/requires.txt
hostout.ubuntu.egg-info/top_level.txt
hostout/ubuntu/README.txt
hostout/ubuntu/__init__.py
hostout/ubuntu/fabfile.py
hostout/ubuntu/tests.py
hostout/ubuntu/newScripts/README
hostout/ubuntu/newScripts/build_python.simple.sh
hostout/ubuntu/newScripts/install.sh
hostout/ubuntu/newScripts/test.sh
hostout/ubuntu/newScripts/helper_scripts/build_libjpeg.sh
hostout/ubuntu/newScripts/helper_scripts/build_python.sh
hostout/ubuntu/newScripts/helper_scripts/build_readline.sh
hostout/ubuntu/newScripts/helper_scripts/build_zlib.sh
hostout/ubuntu/newScripts/helper_scripts/checkLibs.sh