Metadata-Version: 1.0
Name: hostout.ubuntu
Version: 1.0a2
Summary: Plugin for collective.hostout that bootstraps an ubuntu host ready for hostout deployment
Home-page: https://svn.plone.org/svn/collective/hostout.ubuntu
Author: Dylan Jay
Author-email: software@pretaweb.com
License: GPL
Keywords: buildout,fabric,deploy,deployment,server,plone,django,host,hosting
Platform: UNKNOWN
